dobby/__init__.py
dobby/events/__init__.py
dobby/events/base/__init__.py
dobby/events/base/adapters/__init__.py
dobby/events/base/adapters/base_request_adapter.py
dobby/events/base/requests/__init__.py
dobby/events/base/requests/base_request.py
dobby/events/http/__init__.py
dobby/events/http/adapters/__init__.py
dobby/events/http/adapters/http_request_adapter.py
dobby/events/http/requests/__init__.py
dobby/events/http/requests/http_request.py
dobby/events/sns/__init__.py
dobby/events/sns/adapters/__init__.py
dobby/events/sns/adapters/message_list_sns_adapter.py
dobby/events/sns/requests/__init__.py
dobby/events/sns/requests/message_list_sns_request.py
dobby/events/sqs/__init__.py
dobby/events/sqs/adapters/__init__.py
dobby/events/sqs/adapters/message_list_sqs_adapter.py
dobby/events/sqs/requests/__init__.py
dobby/events/sqs/requests/message_list_sqs_request.py
dobby/handlers/__init__.py
dobby/handlers/base_request_handler.py
dobby/handlers/validation_error.py
dobby/responses/__init__.py
dobby/responses/general/__init__.py
dobby/responses/general/general_response.py
dobby/responses/general/general_response_builder.py
dobby/responses/general/runtime_exception.py
dobby/responses/http/__init__.py
dobby/responses/http/builder/__init__.py
dobby/responses/http/builder/http_response_builder.py
dobby/responses/http/response/__init__.py
dobby/responses/http/response/http_response.py
dobby/results/__init__.py
dobby/results/base_result.py
dobby/results/failed_result.py
dobby/results/internal_error_result.py
dobby/results/success_result.py
tests_u/events/__init__.py
tests_u/events/base/__init__.py
tests_u/events/base/adapters/__init__.py
tests_u/events/base/adapters/base_request_adapter_test.py
tests_u/events/base/requests/__init__.py
tests_u/events/base/requests/base_request_test.py
tests_u/events/http/__init__.py
tests_u/events/http/requests/__init__.py
tests_u/events/http/requests/http_request_test.py
tests_u/events/sns/__init__.py
tests_u/events/sns/adapters/__init__.py
dobby-1.5.dist-info/LICENSE
dobby-1.5.dist-info/METADATA
dobby-1.5.dist-info/WHEEL
dobby-1.5.dist-info/top_level.txt
dobby-1.5.dist-info/RECORD
