Metadata-Version: 2.1
Name: dobby
Version: 1.5
Summary: A tiny lambda handler generalizing framework for Python
Home-page: https://github.com/studyportals/Dobby
Author: Addams Family
Author-email: selima@studyportals.com
License: BSD 3-Clause
Platform: UNKNOWN
